{
  "abi_schema_version": "1.0",
  "contract_name": "EventFactory",
  "unique_types": [
    {
      "kind": "void"
    },
    {
      "kind": "int"
    },
    {
      "kind": "slice"
    },
    {
      "kind": "cell"
    },
    {
      "kind": "builder"
    },
    {
      "kind": "bool"
    },
    {
      "kind": "coins"
    },
    {
      "kind": "address"
    },
    {
      "kind": "intN",
      "n": 32
    },
    {
      "kind": "uintN",
      "n": 32
    },
    {
      "kind": "intN",
      "n": 64
    },
    {
      "kind": "uintN",
      "n": 64
    },
    {
      "kind": "StructRef",
      "struct_name": "EventFactoryCreateEvent"
    },
    {
      "kind": "intN",
      "n": 257
    },
    {
      "kind": "string"
    },
    {
      "kind": "EnumRef",
      "enum_name": "EventFactoryErrors"
    },
    {
      "kind": "uintN",
      "n": 16
    },
    {
      "kind": "StructRef",
      "struct_name": "EventFactoryData"
    },
    {
      "kind": "mapKV",
      "key_ty_idx": 13,
      "value_ty_idx": 7
    },
    {
      "kind": "StructRef",
      "struct_name": "EventFactoryEventsResponse"
    },
    {
      "kind": "addressOpt"
    }
  ],
  "struct_instantiations": [],
  "alias_instantiations": [],
  "declarations": [
    {
      "kind": "struct",
      "name": "EventFactoryEventsResponse",
      "ty_idx": 19,
      "fields": [
        {
          "name": "nextId",
          "ty_idx": 13
        },
        {
          "name": "eventsCount",
          "ty_idx": 13
        }
      ]
    },
    {
      "kind": "struct",
      "name": "EventFactoryCreateEvent",
      "ty_idx": 12,
      "prefix": {
        "prefix_num": 636345194,
        "prefix_len": 32
      },
      "fields": [
        {
          "name": "deadline",
          "ty_idx": 13
        },
        {
          "name": "description",
          "ty_idx": 14
        }
      ]
    },
    {
      "kind": "struct",
      "name": "EventFactoryData",
      "ty_idx": 17,
      "fields": [
        {
          "name": "admin",
          "ty_idx": 7
        },
        {
          "name": "feeReceiver",
          "ty_idx": 7
        },
        {
          "name": "feeAmount",
          "ty_idx": 13
        },
        {
          "name": "events",
          "ty_idx": 18
        },
        {
          "name": "nextId",
          "ty_idx": 13
        }
      ]
    },
    {
      "kind": "enum",
      "name": "EventFactoryErrors",
      "ty_idx": 15,
      "encoded_as_ty_idx": 16,
      "members": [
        {
          "name": "StackUnderflow",
          "value": "2",
          "description": "Stack underflow"
        },
        {
          "name": "StackOverflow",
          "value": "3",
          "description": "Stack overflow"
        },
        {
          "name": "IntegerOverflow",
          "value": "4",
          "description": "Integer overflow"
        },
        {
          "name": "IntegerOutOfExpectedRange",
          "value": "5",
          "description": "Integer out of expected range"
        },
        {
          "name": "InvalidOpcode",
          "value": "6",
          "description": "Invalid opcode"
        },
        {
          "name": "TypeCheckError",
          "value": "7",
          "description": "Type check error"
        },
        {
          "name": "CellOverflow",
          "value": "8",
          "description": "Cell overflow"
        },
        {
          "name": "CellUnderflow",
          "value": "9",
          "description": "Cell underflow"
        },
        {
          "name": "DictionaryError",
          "value": "10",
          "description": "Dictionary error"
        },
        {
          "name": "UnknownError",
          "value": "11",
          "description": "'Unknown' error"
        },
        {
          "name": "FatalError",
          "value": "12",
          "description": "Fatal error"
        },
        {
          "name": "OutOfGasError",
          "value": "13",
          "description": "Out of gas error"
        },
        {
          "name": "VirtualizationError",
          "value": "14",
          "description": "Virtualization error"
        },
        {
          "name": "ActionListIsInvalid",
          "value": "32",
          "description": "Action list is invalid"
        },
        {
          "name": "ActionListIsTooLong",
          "value": "33",
          "description": "Action list is too long"
        },
        {
          "name": "ActionIsInvalidOrNotSupported",
          "value": "34",
          "description": "Action is invalid or not supported"
        },
        {
          "name": "InvalidSourceAddressInOutboundMessage",
          "value": "35",
          "description": "Invalid source address in outbound message"
        },
        {
          "name": "InvalidDestinationAddressInOutboundMessage",
          "value": "36",
          "description": "Invalid destination address in outbound message"
        },
        {
          "name": "NotEnoughToncoin",
          "value": "37",
          "description": "Not enough Toncoin"
        },
        {
          "name": "NotEnoughExtraCurrencies",
          "value": "38",
          "description": "Not enough extra currencies"
        },
        {
          "name": "OutboundMessageDoesNotFitIntoACellAfterRewriting",
          "value": "39",
          "description": "Outbound message does not fit into a cell after rewriting"
        },
        {
          "name": "CannotProcessAMessage",
          "value": "40",
          "description": "Cannot process a message"
        },
        {
          "name": "LibraryReferenceIsNull",
          "value": "41",
          "description": "Library reference is null"
        },
        {
          "name": "LibraryChangeActionError",
          "value": "42",
          "description": "Library change action error"
        },
        {
          "name": "ExceededMaximumNumberOfCellsInTheLibraryOrTheMaximumDepthOfTheMerkleTree",
          "value": "43",
          "description": "Exceeded maximum number of cells in the library or the maximum depth of the Merkle tree"
        },
        {
          "name": "AccountStateSizeExceededLimits",
          "value": "50",
          "description": "Account state size exceeded limits"
        },
        {
          "name": "NullReferenceException",
          "value": "128",
          "description": "Null reference exception"
        },
        {
          "name": "InvalidSerializationPrefix",
          "value": "129",
          "description": "Invalid serialization prefix"
        },
        {
          "name": "InvalidIncomingMessage",
          "value": "130",
          "description": "Invalid incoming message"
        },
        {
          "name": "ConstraintsError",
          "value": "131",
          "description": "Constraints error"
        },
        {
          "name": "AccessDenied",
          "value": "132",
          "description": "Access denied"
        },
        {
          "name": "ContractStopped",
          "value": "133",
          "description": "Contract stopped"
        },
        {
          "name": "InvalidArgument",
          "value": "134",
          "description": "Invalid argument"
        },
        {
          "name": "CodeOfAContractWasNotFound",
          "value": "135",
          "description": "Code of a contract was not found"
        },
        {
          "name": "InvalidStandardAddress",
          "value": "136",
          "description": "Invalid standard address"
        },
        {
          "name": "NotABasechainAddress",
          "value": "138",
          "description": "Not a basechain address"
        },
        {
          "name": "WrongSide",
          "value": "3685",
          "description": "Wrong side"
        },
        {
          "name": "BettingClosed",
          "value": "10687",
          "description": "Betting closed"
        },
        {
          "name": "OnlyAdmin",
          "value": "16461",
          "description": "Only admin"
        },
        {
          "name": "OnlyMainAdminCanResolve",
          "value": "19484",
          "description": "Only mainAdmin can resolve"
        },
        {
          "name": "CannotBetBothYesAndNo",
          "value": "20895",
          "description": "Cannot bet both Yes and No"
        },
        {
          "name": "AlreadyResolved",
          "value": "31038",
          "description": "Already resolved"
        },
        {
          "name": "MinValueFeeDeployAmount",
          "value": "33745",
          "description": "Min value = fee + deploy amount"
        },
        {
          "name": "OnlyOwner",
          "value": "35499",
          "description": "Only owner"
        },
        {
          "name": "NoBet",
          "value": "45156",
          "description": "No bet"
        },
        {
          "name": "FactoryAlreadyDeployed",
          "value": "45408",
          "description": "Factory already deployed"
        },
        {
          "name": "NotResolved",
          "value": "58169",
          "description": "Not resolved"
        },
        {
          "name": "AmountMustBePositive",
          "value": "61135",
          "description": "Amount must be positive"
        }
      ]
    }
  ],
  "storage": {
    "storage_ty_idx": 17
  },
  "incoming_messages": [
    {
      "body_ty_idx": 12
    }
  ],
  "incoming_external": [],
  "outgoing_messages": [],
  "emitted_events": [],
  "get_methods": [
    {
      "tvm_method_id": 74901,
      "name": "get_events",
      "parameters": [],
      "return_ty_idx": 19
    },
    {
      "tvm_method_id": 83498,
      "name": "get_event_address",
      "parameters": [
        {
          "name": "id",
          "ty_idx": 13
        }
      ],
      "return_ty_idx": 20
    }
  ],
  "thrown_errors": [
    {
      "kind": "enum_member",
      "name": "EventFactoryErrors.StackUnderflow",
      "description": "Stack underflow",
      "err_code": 2
    },
    {
      "kind": "enum_member",
      "name": "EventFactoryErrors.StackOverflow",
      "description": "Stack overflow",
      "err_code": 3
    },
    {
      "kind": "enum_member",
      "name": "EventFactoryErrors.IntegerOverflow",
      "description": "Integer overflow",
      "err_code": 4
    },
    {
      "kind": "enum_member",
      "name": "EventFactoryErrors.IntegerOutOfExpectedRange",
      "description": "Integer out of expected range",
      "err_code": 5
    },
    {
      "kind": "enum_member",
      "name": "EventFactoryErrors.InvalidOpcode",
      "description": "Invalid opcode",
      "err_code": 6
    },
    {
      "kind": "enum_member",
      "name": "EventFactoryErrors.TypeCheckError",
      "description": "Type check error",
      "err_code": 7
    },
    {
      "kind": "enum_member",
      "name": "EventFactoryErrors.CellOverflow",
      "description": "Cell overflow",
      "err_code": 8
    },
    {
      "kind": "enum_member",
      "name": "EventFactoryErrors.CellUnderflow",
      "description": "Cell underflow",
      "err_code": 9
    },
    {
      "kind": "enum_member",
      "name": "EventFactoryErrors.DictionaryError",
      "description": "Dictionary error",
      "err_code": 10
    },
    {
      "kind": "enum_member",
      "name": "EventFactoryErrors.UnknownError",
      "description": "'Unknown' error",
      "err_code": 11
    },
    {
      "kind": "enum_member",
      "name": "EventFactoryErrors.FatalError",
      "description": "Fatal error",
      "err_code": 12
    },
    {
      "kind": "enum_member",
      "name": "EventFactoryErrors.OutOfGasError",
      "description": "Out of gas error",
      "err_code": 13
    },
    {
      "kind": "enum_member",
      "name": "EventFactoryErrors.VirtualizationError",
      "description": "Virtualization error",
      "err_code": 14
    },
    {
      "kind": "enum_member",
      "name": "EventFactoryErrors.ActionListIsInvalid",
      "description": "Action list is invalid",
      "err_code": 32
    },
    {
      "kind": "enum_member",
      "name": "EventFactoryErrors.ActionListIsTooLong",
      "description": "Action list is too long",
      "err_code": 33
    },
    {
      "kind": "enum_member",
      "name": "EventFactoryErrors.ActionIsInvalidOrNotSupported",
      "description": "Action is invalid or not supported",
      "err_code": 34
    },
    {
      "kind": "enum_member",
      "name": "EventFactoryErrors.InvalidSourceAddressInOutboundMessage",
      "description": "Invalid source address in outbound message",
      "err_code": 35
    },
    {
      "kind": "enum_member",
      "name": "EventFactoryErrors.InvalidDestinationAddressInOutboundMessage",
      "description": "Invalid destination address in outbound message",
      "err_code": 36
    },
    {
      "kind": "enum_member",
      "name": "EventFactoryErrors.NotEnoughToncoin",
      "description": "Not enough Toncoin",
      "err_code": 37
    },
    {
      "kind": "enum_member",
      "name": "EventFactoryErrors.NotEnoughExtraCurrencies",
      "description": "Not enough extra currencies",
      "err_code": 38
    },
    {
      "kind": "enum_member",
      "name": "EventFactoryErrors.OutboundMessageDoesNotFitIntoACellAfterRewriting",
      "description": "Outbound message does not fit into a cell after rewriting",
      "err_code": 39
    },
    {
      "kind": "enum_member",
      "name": "EventFactoryErrors.CannotProcessAMessage",
      "description": "Cannot process a message",
      "err_code": 40
    },
    {
      "kind": "enum_member",
      "name": "EventFactoryErrors.LibraryReferenceIsNull",
      "description": "Library reference is null",
      "err_code": 41
    },
    {
      "kind": "enum_member",
      "name": "EventFactoryErrors.LibraryChangeActionError",
      "description": "Library change action error",
      "err_code": 42
    },
    {
      "kind": "enum_member",
      "name": "EventFactoryErrors.ExceededMaximumNumberOfCellsInTheLibraryOrTheMaximumDepthOfTheMerkleTree",
      "description": "Exceeded maximum number of cells in the library or the maximum depth of the Merkle tree",
      "err_code": 43
    },
    {
      "kind": "enum_member",
      "name": "EventFactoryErrors.AccountStateSizeExceededLimits",
      "description": "Account state size exceeded limits",
      "err_code": 50
    },
    {
      "kind": "enum_member",
      "name": "EventFactoryErrors.NullReferenceException",
      "description": "Null reference exception",
      "err_code": 128
    },
    {
      "kind": "enum_member",
      "name": "EventFactoryErrors.InvalidSerializationPrefix",
      "description": "Invalid serialization prefix",
      "err_code": 129
    },
    {
      "kind": "enum_member",
      "name": "EventFactoryErrors.InvalidIncomingMessage",
      "description": "Invalid incoming message",
      "err_code": 130
    },
    {
      "kind": "enum_member",
      "name": "EventFactoryErrors.ConstraintsError",
      "description": "Constraints error",
      "err_code": 131
    },
    {
      "kind": "enum_member",
      "name": "EventFactoryErrors.AccessDenied",
      "description": "Access denied",
      "err_code": 132
    },
    {
      "kind": "enum_member",
      "name": "EventFactoryErrors.ContractStopped",
      "description": "Contract stopped",
      "err_code": 133
    },
    {
      "kind": "enum_member",
      "name": "EventFactoryErrors.InvalidArgument",
      "description": "Invalid argument",
      "err_code": 134
    },
    {
      "kind": "enum_member",
      "name": "EventFactoryErrors.CodeOfAContractWasNotFound",
      "description": "Code of a contract was not found",
      "err_code": 135
    },
    {
      "kind": "enum_member",
      "name": "EventFactoryErrors.InvalidStandardAddress",
      "description": "Invalid standard address",
      "err_code": 136
    },
    {
      "kind": "enum_member",
      "name": "EventFactoryErrors.NotABasechainAddress",
      "description": "Not a basechain address",
      "err_code": 138
    },
    {
      "kind": "enum_member",
      "name": "EventFactoryErrors.WrongSide",
      "description": "Wrong side",
      "err_code": 3685
    },
    {
      "kind": "enum_member",
      "name": "EventFactoryErrors.BettingClosed",
      "description": "Betting closed",
      "err_code": 10687
    },
    {
      "kind": "enum_member",
      "name": "EventFactoryErrors.OnlyAdmin",
      "description": "Only admin",
      "err_code": 16461
    },
    {
      "kind": "enum_member",
      "name": "EventFactoryErrors.OnlyMainAdminCanResolve",
      "description": "Only mainAdmin can resolve",
      "err_code": 19484
    },
    {
      "kind": "enum_member",
      "name": "EventFactoryErrors.CannotBetBothYesAndNo",
      "description": "Cannot bet both Yes and No",
      "err_code": 20895
    },
    {
      "kind": "enum_member",
      "name": "EventFactoryErrors.AlreadyResolved",
      "description": "Already resolved",
      "err_code": 31038
    },
    {
      "kind": "enum_member",
      "name": "EventFactoryErrors.MinValueFeeDeployAmount",
      "description": "Min value = fee + deploy amount",
      "err_code": 33745
    },
    {
      "kind": "enum_member",
      "name": "EventFactoryErrors.OnlyOwner",
      "description": "Only owner",
      "err_code": 35499
    },
    {
      "kind": "enum_member",
      "name": "EventFactoryErrors.NoBet",
      "description": "No bet",
      "err_code": 45156
    },
    {
      "kind": "enum_member",
      "name": "EventFactoryErrors.FactoryAlreadyDeployed",
      "description": "Factory already deployed",
      "err_code": 45408
    },
    {
      "kind": "enum_member",
      "name": "EventFactoryErrors.NotResolved",
      "description": "Not resolved",
      "err_code": 58169
    },
    {
      "kind": "enum_member",
      "name": "EventFactoryErrors.AmountMustBePositive",
      "description": "Amount must be positive",
      "err_code": 61135
    }
  ],
  "compiler_name": "tolk",
  "compiler_version": "1.4.2"
}
